systemeye/__init__.py
systemeye/toolbox.py
systemeye-0.0.1.dist-info/LICENSE.txt
systemeye-0.0.1.dist-info/METADATA
systemeye-0.0.1.dist-info/WHEEL
systemeye-0.0.1.dist-info/top_level.txt
systemeye-0.0.1.dist-info/RECORD
